teamhack_restify/__init__.py
teamhack_restify/__main__.py
teamhack_restify/server.py
teamhack_restify-0.0.5.dist-info/LICENSE
teamhack_restify-0.0.5.dist-info/METADATA
teamhack_restify-0.0.5.dist-info/WHEEL
teamhack_restify-0.0.5.dist-info/top_level.txt
teamhack_restify-0.0.5.dist-info/RECORD
