Metadata-Version: 2.1
Name: teamhack-restify
Version: 0.0.5
Summary: Hack the Box Team Support Services
License-File: LICENSE
Requires-Dist: flask
Requires-Dist: json
Requires-Dist: xmltodict
Provides-Extra: rel
Requires-Dist: twine ; extra == 'rel'
Provides-Extra: test
Requires-Dist: coverage ; extra == 'test'
Requires-Dist: pytest ; extra == 'test'
